{
  "parent": "charm:astrolabes/link_astrolabe",
  "display": {
    "icon": {
      "item": "charm:astrolabe"
    },
    "title": {
      "translate": "advancements.charm.locate_astrolabe_location.title"
    },
    "description": {
      "translate": "advancements.charm.locate_astrolabe_location.description"
    },
    "frame": "challenge",
    "show_toast": true,
    "announce_to_chat": false,
    "hidden": false
  },
  "criteria": {
    "located_astrolabe_location": {
      "trigger": "charm:action_performed",
      "conditions": {
        "action": "charm:located_astrolabe_location"
      }
    }
  },
  "requirements": [
    [
      "located_astrolabe_location"
    ]
  ]
}